bioturbation/__init__.py
bioturbation/model.py
bioturbation/soil.py
bioturbation-1.0.1.dist-info/LICENSE
bioturbation-1.0.1.dist-info/METADATA
bioturbation-1.0.1.dist-info/WHEEL
bioturbation-1.0.1.dist-info/top_level.txt
bioturbation-1.0.1.dist-info/RECORD
