Metadata-Version: 2.1
Name: bioturbation
Version: 1.0.1
Summary: Model of earthworm bioturbation in a layered soil profile
Home-page: https://github.com/samharrison7/bioturbation-model
Author: Sam Harrison
Author-email: samharrison.xg@gmail.com
License: UNKNOWN
Project-URL: Bug Tracker, https://github.com/samharrison7/bioturbation-model/issues
Platform: UNKNOWN
Classifier: Programming Language :: Python :: 3
Classifier: License :: OSI Approved :: BSD License
Classifier: Operating System :: OS Independent
Requires-Python: >=3.6
License-File: LICENSE
Requires-Dist: numpy
Requires-Dist: scipy
Requires-Dist: pandas
Requires-Dist: plotly
